oresat_cfc/__init__.py
oresat_cfc/__main__.py
oresat_cfc/_version.py
oresat_cfc/drivers/__init__.py
oresat_cfc/drivers/pirt1280.py
oresat_cfc/drivers/rc625.py
oresat_cfc/services/__init__.py
oresat_cfc/services/camera.py
oresat_cfc/services/tec_controller.py
oresat_cfc/templates/cfc.html
oresat_cfc/templates/pid.html
tests/__init__.py
tests/drivers/__init__.py
tests/drivers/test_pirt1280.py
tests/services/__init__.py
oresat_cfc-0.1.1.dist-info/LICENSE
oresat_cfc-0.1.1.dist-info/METADATA
oresat_cfc-0.1.1.dist-info/WHEEL
oresat_cfc-0.1.1.dist-info/entry_points.txt
oresat_cfc-0.1.1.dist-info/top_level.txt
oresat_cfc-0.1.1.dist-info/RECORD
