Metadata-Version: 2.1
Name: oresat-cfc
Version: 0.1.1
Summary: OreSat CFC OLAF app
License: GPL-3.0
Classifier: License :: OSI Approved :: GNU General Public License v3 (GPLv3)
Classifier: Operating System :: POSIX :: Linux
Classifier: Programming Language :: Python :: 3
Classifier: Programming Language :: Python :: 3.7
Classifier: Programming Language :: Python :: 3.8
Classifier: Programming Language :: Python :: 3.9
Classifier: Programming Language :: Python :: 3.10
Classifier: Programming Language :: Python :: 3.11
Classifier: Topic :: Software Development :: Embedded Systems
Requires-Python: >=3.7
License-File: LICENSE
Requires-Dist: numpy
Requires-Dist: opencv-python-headless ==4.6.0.66
Requires-Dist: oresat-configs
Requires-Dist: oresat-olaf >=3.4.0
Requires-Dist: simple-pid
Requires-Dist: spidev
Requires-Dist: tifffile
Requires-Dist: matplotlib
